{"forum": {"content": "\u4f86\u311b<br /><br /><br />\u5c31\u662f\u9019\u6a23<br /><br /><br />\u906e\u9ed1\u773c\u5708\u311a\u311a\u311a\u311a<br /><br /><br />\u5728\u4f86\u4e0a\u9694\u96e2\uff0c\u90a3\u4e9b", "images": ["http://filestoresg1.beetalkmobile.com:8081/file/563f8ccb29973dedbb330f03d53538cf", "http://filestoresg1.beetalkmobile.com:8081/file/8709df4f0bf340fdc8a3f8a3fcd7b04a", "http://filestoresg1.beetalkmobile.com:8081/file/0d6f2cda257c942301c90d8100224142"], "urls": [], "title": "\u53e3\u7d05\u9019\u6a23\u5316\uff5e\uff5e\uff5e"}, "threadStatus": 0, "regionId": 886, "barStatus": 0, "barId": 4, "postBy": {"utc": 1472958375000, "level": 11, "location": "\u9ad8\u96c4\u5e02\u00b7\u53f0\u7063", "avatar": "http://filestoresg1.beetalkmobile.com:8081/file/8602565782796723027", "name": "\u661f\u947d\ud83d\udc8e"}, "id": 4433972}
