{"forum": {"content": "\u6709\u9a0eT-MAX\u7684\u597d\u53cb\u561b\uff1f\u79ae\u62dc\u516d\u665a\u4e0a\u60f3\u7d04\u8dd1\u967d\u660e\u5c71^_^", "images": ["http://filestoresg1.beetalkmobile.com:8081/file/124d7b8bc59ba701c6b7bece3a2f94a9"], "urls": [], "title": "\u7d04\u8dd1"}, "threadStatus": 0, "regionId": 886, "barStatus": 0, "barId": 816, "postBy": {"utc": 1479130153000, "level": 12, "location": "\u65b0\u5317\u5e02\u00b7\u53f0\u7063", "avatar": "http://filestoresg1.beetalkmobile.com:8081/file/-1600820754275207018", "name": "\u98a8\u75d5"}, "id": 4863429}
