{"forum": {"content": "\u4ea4\u500b\u670b\u53cb\u5427\uff01<br />\u6216\u8a31\u53ef\u4ee5\u5728\u6709\u66f4\u9032\u4e00\u6b65\u7684\u95dc\u4fc2\u2764\ufe0f<br /><br />\u4e0d\u8981\u4e00\u958b\u53e3\u5c31\u804a\u8272\uff0c\u6211\u6703\u53d7\u4e0d\u4e86\ud83d\ude12\ud83e\udd14<br /><br />\u6211\u662f\u7537\u751f\ud83d\ude36", "images": ["http://filestoresg1.beetalkmobile.com:8081/file/6d0fca26ebe85c026b9f3954f6dbdf56", "http://filestoresg1.beetalkmobile.com:8081/file/be999f00e0291d41c7dbeda01c19a174", "http://filestoresg1.beetalkmobile.com:8081/file/f0841ea996db4156da24cac8785a88e2"], "urls": [], "title": "\u4f86\u8a8d\u8b58\u6211\u263a\ufe0f"}, "threadStatus": 0, "regionId": 886, "barStatus": 0, "barId": 20, "postBy": {"utc": 1468899994000, "level": 4, "location": "", "avatar": "http://filestoresg1.beetalkmobile.com:8081/file/1084287796664774401", "name": "\u8a60\u3126"}, "id": 4135511}
