{"forum": {"content": "\u5feb\u4f86\u4e00\u8d77\u5206\u4eab\u5427\uff01\uff01", "images": ["http://filestoresg1.beetalkmobile.com:8081/file/33f923460fb45b4ec7ee597bd985c397", "http://filestoresg1.beetalkmobile.com:8081/file/83a26ff9e93f58d2ead9775b0f205d34"], "urls": [], "title": "\u6709\u4eba\u8ddf\u6211\u4e00\u6a23\u71b1\u611b\u5f80\u5c71\u4e0a\u8dd1\u3001\u770b\u98a8\u666f\u7684\u55ce\uff1f\uff01"}, "threadStatus": 0, "regionId": 886, "barStatus": 0, "barId": 604, "postBy": {"utc": 1479814532000, "level": 2, "location": "\u5b9c\u862d\u7e23\u00b7\u53f0\u7063", "avatar": "http://filestoresg1.beetalkmobile.com:8081/file/-2635652505899298392", "name": "\ud83d\ude33"}, "id": 4909992}
