{"forum": {"content": "\u5b89\u5b89 \u6211\u662f105\u7b2c\u4e94\u68af<br />\u6709\u540c\u6642\u9593\u4e0a\u6210\u529f\u5dba\u7684\u540c\u4f34\u55ce", "images": ["http://filestoresg1.beetalkmobile.com:8081/file/0175a06dc22b7dfd1141dd29ea4d7069"], "urls": [], "title": "\u627e\u516b\u6708\u5341\u865f\u7684\u5fd7\u9858\u5f79"}, "threadStatus": 0, "regionId": 886, "barStatus": 0, "barId": 704, "postBy": {"utc": 1469609998000, "level": 2, "location": "\u53f0\u4e2d\u5e02\u00b7\u53f0\u7063", "avatar": "http://filestoresg1.beetalkmobile.com:8081/file/342505579449717482", "name": "lancer \u7ffc"}, "id": 4188444}
