{"forum": {"content": "\u6253AR\u5c45\u591a\ud83d\ude0f<br /><br />ID\uff1aTheOlnyPrincess\u502a", "images": ["http://filestoresg1.beetalkmobile.com:8081/file/adec6ac5f248ac238bdee8e0d3e48e0b"], "urls": [], "title": "\u4e0d\u6015\u96f7\u5c31+\u597d\u53cb\u5427\ud83d\udc8b"}, "threadStatus": 0, "regionId": 886, "barStatus": 0, "barId": 60, "postBy": {"utc": 1469608633000, "level": 2, "location": "\u65b0\u5317\u5e02\u00b7\u53f0\u7063", "avatar": "http://filestoresg1.beetalkmobile.com:8081/file/59545164226215697", "name": "\u5f08\u3126\u2665"}, "id": 4188334}
