{"forum": {"content": "\u5176\u5be6\u4f86\u9019\u88e1\u627e\u6211<br />\u6211\u6703\u66f4\u958b\u5fc3\ud83d\udc8b", "images": ["http://filestoresg1.beetalkmobile.com:8081/file/100c8ba1ca3f83e0eb3eff2693067956"], "urls": [], "title": "\u627e\u6211\u627e\u6211"}, "threadStatus": 1, "regionId": 886, "barStatus": 0, "barId": 767, "postBy": {"utc": 1474217045000, "level": 2, "location": "\u53f0\u4e2d\u5e02\u00b7\u53f0\u7063", "avatar": "http://filestoresg1.beetalkmobile.com:8081/file/-4436399656185416607", "name": "\u53ef\u4ee5"}, "id": 4526563}
