{"forum": {"content": "\u4e0d\u597d\u610f\u601d\u6211180\u7684\u7537\u670b\u53cb\u5931\u8e64\u4e86\ud83d\ude48<br />\u6709\u6c92\u6709\u4eba\u5e6b\u6211\u627e\u4e00\u4e0b180\u7684\u7537\u53cb\ud83d\ude4b\ud83c\udffb\ud83d\ude4b\ud83c\udffb\ud83d\ude4b\ud83c\udffb\ud83d\ude4b\ud83c\udffb<br />\u8ddf\u4ed6\u8aaa\u6211\u5728\u9019\u908a\u7b49\u4ed6\u54c8\u54c8<br /><br /><br />-158\u8ff7\u8def\u7684\u5c0f\u5973\u5b69", "images": ["http://filestoresg1.beetalkmobile.com:8081/file/793e038ef10b7e3ded22c630f38de128"], "urls": [], "title": "180\u7684\u7537\u751f"}, "threadStatus": 0, "regionId": 886, "barStatus": 0, "barId": 205, "postBy": {"utc": 1471706224000, "level": 3, "location": "\u6843\u5712\u5e02\u00b7\u53f0\u7063", "avatar": "http://filestoresg1.beetalkmobile.com:8081/file/-1762584208273023488", "name": "\u4f69\u5b9c\ud83d\udc8b"}, "id": 4340653}
