{"forum": {"content": "\u6211\u9ad4\u91cd\u5f88\u8f15\u808c\u8089\u5f88\u591a\u529b\u91cf\u5f88\u5927\u80fd\u91cf\u5f88\u5f37", "images": ["http://filestoresg1.beetalkmobile.com:8081/file/4597cbd67ac8c57cf44eaad0b2fcedab", "http://filestoresg1.beetalkmobile.com:8081/file/1d31246a0fc5993c9d132c38c2062a02", "http://filestoresg1.beetalkmobile.com:8081/file/170c8b1f9d92d8d77fdbc40f452eb0b1", "http://filestoresg1.beetalkmobile.com:8081/file/9e2f932d12c4edce8f9f7f16323a5a5a", "http://filestoresg1.beetalkmobile.com:8081/file/d9d688f0d46063b8bac42d9d79fdc54d"], "urls": [], "title": "\u9ec3\u91d1\u6bd4\u4f8b"}, "threadStatus": 0, "regionId": 886, "barStatus": 0, "barId": 66, "postBy": {"utc": 1475192479000, "level": 23, "location": "\u65b0\u5317\u5e02\u00b7\u53f0\u7063", "avatar": "http://filestoresg1.beetalkmobile.com:8081/file/7677580735481099924", "name": "Kevin885511"}, "id": 4595306}
