{"forum": {"content": "\u5982\u984c", "images": ["http://filestoresg1.beetalkmobile.com:8081/file/6b5fb788cb6dcfd522b8febe3d44d565"], "urls": [], "title": "\u627e\u500b\u4f34 \u4e00\u8d77\u8de8\u5e74 \uff08\u5973\u751f\uff09"}, "threadStatus": 1, "regionId": 886, "barStatus": 0, "barId": 205, "postBy": {"utc": 1480661167000, "level": 3, "location": "\u65b0\u5317\u5e02\u00b7\u53f0\u7063", "avatar": "http://filestoresg1.beetalkmobile.com:8081/file/3006389147529657247", "name": "\u99ac\u514b"}, "id": 4965944}
