{"forum": {"content": "\u4e0d\u662f\u5f88\u5e73\u50f9\u554a\ud83d\ude2b", "images": ["http://filestoresg1.beetalkmobile.com:8081/file/b0d24be5cf0d16c7c5ac758ccea6e810", "http://filestoresg1.beetalkmobile.com:8081/file/134adc6dc6898f8f3f4d7a60e05c6f4c", "http://filestoresg1.beetalkmobile.com:8081/file/5b20a5f48a2bea0e02072ee4d775ce45"], "urls": [], "title": "\u5927\u76f4\u73cd\u6709\u798f(Jouful)"}, "threadStatus": 0, "regionId": 886, "barStatus": 0, "barId": 98, "postBy": {"utc": 1479118032000, "level": 17, "location": "\u53f0\u5317\u5e02\u00b7\u53f0\u7063", "avatar": "http://filestoresg1.beetalkmobile.com:8081/file/8409351918908481821", "name": "\u8521\u963f\u68ee"}, "id": 4862416}
