{"forum": {"content": "\u4f86\u8a8d\u8b58\u5427\uff01\u4f60\u5011\u5462\uff1f\u4f4f\u90a3\u5152", "images": ["http://filestoresg1.beetalkmobile.com:8081/file/d99615d34590bc846bcc9fe41cb6e210", "http://filestoresg1.beetalkmobile.com:8081/file/b45f0a8336565bb70236a1579a0e4a3f", "http://filestoresg1.beetalkmobile.com:8081/file/2f20afaaef3f3a1f59bd939c2ec4de74", "http://filestoresg1.beetalkmobile.com:8081/file/4ad55befab9791b4b0a57b79aa66e35c"], "urls": [], "title": "82\u5e74\u6b21 \u4f4f\u82d7\u6817-\u982d\u4efd"}, "threadStatus": 0, "regionId": 886, "barStatus": 0, "barId": 748, "postBy": {"utc": 1474975881000, "level": 2, "location": "\u82d7\u6817\u7e23\u00b7\u53f0\u7063", "avatar": "http://filestoresg1.beetalkmobile.com:8081/file/-6417570081272623461", "name": "\u2192\u5c0f\u32a3\u5bf6\u2190"}, "id": 4580090}
