{"forum": {"content": "\u5982\u984c", "images": ["http://filestoresg1.beetalkmobile.com:8081/file/20e6d3b9f5e802b92c7a55ed42ae707a"], "urls": [], "title": "\u53ea\u80fd\u8aaa\u3002\u4eba\u771f\u7684\u5c31\u662f\u7de3\u4efd\u3002\u3002"}, "threadStatus": 1, "regionId": 886, "barStatus": 0, "barId": 13, "postBy": {"utc": 1478853111000, "level": 0, "location": "\u65b0\u5317\u5e02\u00b7\u53f0\u7063", "avatar": "http://filestoresg1.beetalkmobile.com:8081/file/-117111162111059947", "name": "\u2122\ufe0f\u539f\u771f\u3299\ufe0fCafe"}, "id": 4843677}
