{"forum": {"content": "\u53ea\u662f\u60f3\u8981\u4e00\u500b\u90a3\u9ebc\u5e73\u51e1\u7c21\u55ae\u7684\u611b\u60c5<br />\u5c31\u600e\u9ebc\u7684\u7c21\u7c21\u55ae\u55ae\u7684\u6709\u90a3\u9ebc\u7684\u56f0\u96e3\u55ce\uff1f<br /><br />\u300e\u5176\u5be6\u60f3\u8981\u7684\u4e26\u4e0d\u591a\u5c31\u90a3\u9ebc\u7c21\u55ae\u5169\u500b\u5b57\u300f<br /><br />\u4f46\u4f9d\u7136\u9084\u662f\u8981\u4e92\u76f8\u5305\u5bb9\u7b49\u7b49....\u5c0d\u5427", "images": ["http://filestoresg1.beetalkmobile.com:8081/file/1ebd8bf5fb9c35976f31d1b03c7af021"], "urls": [], "title": "\u5e73\u51e1\u7c21\u55ae\u6709\u90a3\u9ebc\u96e3\u55ce\ud83d\ude14"}, "threadStatus": 0, "regionId": 886, "barStatus": 0, "barId": 13, "postBy": {"utc": 1468707861000, "level": 3, "location": "\u65b0\u5317\u5e02\u00b7\u53f0\u7063", "avatar": "http://filestoresg1.beetalkmobile.com:8081/file/4732699385263741078", "name": "\u2764 I miss Kiss U"}, "id": 4121215}
