{"forum": {"content": "\u5343\u842c\u4e0d\u8981\u60f9\u6012\u5973\u6027 \uff08\u6296<br />\u5149\u675f\u5f69\u5e36\u8b8a\u6210\u528d\uff01<br />\u7c21\u55ae\u7684\u9020\u578b\u8207\u914d\u8272\uff0c<br />\u5c31\u80fd\u5c55\u73fe\u51fa\u72c2\u66b4\u6a21\u5f0f<br />\u5e0c\u671b\u4e0b\u4e00\u96bb\u6703\u662fMG\u5927\u5e2b\u92fc\u5f48", "images": ["http://filestoresg1.beetalkmobile.com:8081/file/04c0b2fb8dffeb8d23944567574f362d", "http://filestoresg1.beetalkmobile.com:8081/file/706f8945a6e69e11033b43b69011a1f1", "http://filestoresg1.beetalkmobile.com:8081/file/a6212159dc1a74e6e93cc15c87262c33", "http://filestoresg1.beetalkmobile.com:8081/file/cf39bdc5392630b54c0727854ceed13f", "http://filestoresg1.beetalkmobile.com:8081/file/e0b16c8d637e28d59870bf26928ea028", "http://filestoresg1.beetalkmobile.com:8081/file/53acbcaedde4d62dfc84ee84c6f9e947"], "urls": [], "title": "HG 1/144 \u72c2\u66b4\u8afe\u8c9d\u723e\u92fc\u5f48"}, "threadStatus": 0, "regionId": 886, "barStatus": 0, "barId": 207, "postBy": {"utc": 1478871868000, "level": 2, "location": "", "avatar": "http://filestoresg1.beetalkmobile.com:8081/file/-4587898065715567053", "name": "\u4fdd\u5065\u65b0\u8cb4\u51f1\u6587"}, "id": 4845170}
