{"forum": {"content": "  ", "images": ["http://filestoresg1.beetalkmobile.com:8081/file/b726737cf3b57a086fde586a044e39fd", "http://filestoresg1.beetalkmobile.com:8081/file/c33420371b185140c93eeff56bf97daa"], "urls": [], "title": "\u65e9\u9ede\u7761"}, "threadStatus": 0, "regionId": 886, "barStatus": 0, "barId": 10, "postBy": {"utc": 1472392722000, "level": 16, "location": "\u65b0\u5317\u5e02\u00b7\u53f0\u7063", "avatar": "http://filestoresg1.beetalkmobile.com:8081/file/4048909807377316629", "name": "\u767d\u7c73"}, "id": 4392557}
