{"forum": {"content": "\u55ae\u773c\u76ae\ud83d\ude2d\ud83d\ude2d\ud83d\ude2d\u4e0d\u840c\ud83d\udc15\ud83d\udc15", "images": ["http://filestoresg1.beetalkmobile.com:8081/file/a34a9f58b019f494e2066c2d4727f014"], "urls": [], "title": "\u55ae\u773c\u76ae"}, "threadStatus": 1, "regionId": 886, "barStatus": 0, "barId": 205, "postBy": {"utc": 1477592313000, "level": 6, "location": "\u53f0\u5317\u5e02\u00b7\u53f0\u7063", "avatar": "http://filestoresg1.beetalkmobile.com:8081/file/-3480108228409978139", "name": "\ud83c\udf38\ud83c\udf38SK\ud83d\udc9c"}, "id": 4757364}
