{"forum": {"content": "\u9047\u5230\u5947\u8469 \u5c31\u662f\u5404\u7a2e\u7121\u5948\u3002\u3002", "images": ["http://filestoresg1.beetalkmobile.com:8081/file/c55b5afb8d94f07b0429f75de759a640"], "urls": [], "title": "\u54a6\ud83d\ude27"}, "threadStatus": 0, "regionId": 886, "barStatus": 0, "barId": 4, "postBy": {"utc": 1476974009000, "level": 2, "location": "\u65b0\u5317\u5e02\u00b7\u53f0\u7063", "avatar": "http://filestoresg1.beetalkmobile.com:8081/file/-6377679808492672083", "name": "\u5bf6\u5bf6"}, "id": 4712333}
