{"forum": {"content": "\u98b1\u98a8\u53c8\u8981\u4f86\u4e86<br />\u4e2d\u79cb\u7bc0\u4e5f\u5feb\u5230\u4e86<br />\u8077\u696d\u8ecd\u4eba\u5011\u4f60\u5011\u53c8\u8981\u5fd9\u4e86<br />\u8f9b\u82e6\u4e86<br />\u52a0\u6cb9<br />\u795d\u4f60\u5011\u4e2d\u79cb\u7bc0\u5feb\u6a02<br />\u4f60\u5011\u662f\u6700\u68d2\u7684<br />\u8f9b\u82e6\u4f60\u5011\u4e86<br />", "images": ["http://filestoresg1.beetalkmobile.com:8081/file/75df96fe950e04eb538e7b46a8588239"], "urls": [], "title": "\u8f9b\u82e6\u4f60\u5011\u4e86"}, "threadStatus": 0, "regionId": 886, "barStatus": 0, "barId": 704, "postBy": {"utc": 1473777303000, "level": 15, "location": "\u53f0\u5357\u5e02\u00b7\u53f0\u7063", "avatar": "http://filestoresg1.beetalkmobile.com:8081/file/512083250544070666", "name": "\u85cd\u599e"}, "id": 4494070}
