{"forum": {"content": "\u7f8e\u9e97\u7684\u6d77\u5e95", "images": ["http://filestoresg1.beetalkmobile.com:8081/file/cb155c860bfa2021a4b6a15a067598cc", "http://filestoresg1.beetalkmobile.com:8081/file/502b4ec900385d84f9f4875ea4b2f406", "http://filestoresg1.beetalkmobile.com:8081/file/6d6390ed83e62c36835a3ac0033f9dee", "http://filestoresg1.beetalkmobile.com:8081/file/f54b4de98131e7befa0118ccfea317f9", "http://filestoresg1.beetalkmobile.com:8081/file/4ed7b09c30c35cc3023ad2626800c7d6", "http://filestoresg1.beetalkmobile.com:8081/file/caee1d4879f92235b6d58adb576065f8"], "urls": [], "title": "2016/1103-06"}, "threadStatus": 0, "regionId": 886, "barStatus": 0, "barId": 85, "postBy": {"utc": 1478622121000, "level": 10, "location": "\u6843\u5712\u5e02\u00b7\u53f0\u7063", "avatar": "http://filestoresg1.beetalkmobile.com:8081/file/-2157832249580413678", "name": "Leslie"}, "id": 4828646}
