{"forum": {"content": "\u53f0\u9435\u7684\u5340\u9593\u600e\u9ebc\u8ddf\u8392\u5149\u5dee\u4e0d\u591a\u6642\u9593\u8eca\u7a0b<br />\u53ea\u6709\u50f9\u9322\u6bd4\u8f03\u4e0d\u4e00\u6a23", "images": ["http://filestoresg1.beetalkmobile.com:8081/file/b011cc98900f0a9da07b3849bf0f2378"], "urls": [], "title": "\u53f0\u9435\u7684\ud83d\ude84\u8392\u5149\u22ef\u22ef"}, "threadStatus": 0, "regionId": 886, "barStatus": 0, "barId": 10, "postBy": {"utc": 1477731618000, "level": 2, "location": "\u6843\u5712\u5e02\u00b7\u53f0\u7063", "avatar": "http://filestoresg1.beetalkmobile.com:8081/file/-6418197912753358329", "name": "\u6afb\u6afb\u7f8e\u9edb\u5b50"}, "id": 4766247}
