{"forum": {"content": "\u4eca\u5929\u751f\u65e5\u53ef\u4ee5\u7d66\u6211\u500b\u795d\u798f\u55ce\u2728<br /><br />\u96d6\u7136\u4eca\u5e74\u5df2\u7d93\u662f25\u6b72\u7684\u8001\u59d0\u59d0\u4e86", "images": ["http://filestoresg1.beetalkmobile.com:8081/file/796df999c26eedd01f7b6397ba4a81f9"], "urls": [], "title": "\u751f\u65e5"}, "threadStatus": 0, "regionId": 886, "barStatus": 0, "barId": 205, "postBy": {"utc": 1468002854000, "level": 3, "location": "", "avatar": "http://filestoresg1.beetalkmobile.com:8081/file/-4012948059948427007", "name": "Jean"}, "id": 4071348}
