{"forum": {"content": "\u53f0\u5357\u4eba\ud83d\udc4b\ud83d\udc4b<br />\u4e00\u500b158\u7684\u5c0f\u77ee\u5b50<br />\u8d95\u5feb\u4f86\u8ddf\u6211\u52a0\u597d\u53cb\u5427\ud83d\ude18\ud83d\ude18<br />\u55ae\u8eab\u55ae\u8eab\u5566\ud83d\ude2d\ud83d\ude2d\ud83d\ude2d<br />\uff08\u7167\u7247\u90a3\u500b\u81c9\u771f\u7684\u5f88\u602a\ud83d\ude02", "images": ["http://filestoresg1.beetalkmobile.com:8081/file/08cf9ffb7a6c1a46af11e9b4cad203c5"], "urls": [], "title": "\u8a8d\u8b58\ud83d\ude0e"}, "threadStatus": 0, "regionId": 886, "barStatus": 0, "barId": 20, "postBy": {"utc": 1468504417000, "level": 7, "location": "", "avatar": "http://filestoresg1.beetalkmobile.com:8081/file/-5010461287834160615", "name": "\u314b"}, "id": 4106852}
