{"forum": {"content": "\u611f\u60c5\u7684\u4e16\u754c\uff0c\u8dcc\u8dcc\u649e\u649e\uff0c\u53d7\u4e86\u50b7\u4e0d\u77e5\u9053\u600e\u9ebc\u7642\u50b7\uff0c\u6211\u5c31\u662f\u6211<br />\u60f3\u50cf\u516c\u4e3b\u4e00\u6a23\u88ab\u5bf5\u8457\u88ab\u75bc\u611b\uff0c\u6216\u8a31\u6211\u4e0d\u5920\u8cc7\u683c\u55ce\uff1f\u60f3\u627e\u4e00\u500b\u8996\u70ba\u6211\u516c\u4e3b\u7684\u4eba\uff0c\uff0c\uff0c\uff0c\u592a\u96e3", "images": ["http://filestoresg1.beetalkmobile.com:8081/file/6b1e2ab7c06fd14074365984300fbddf"], "urls": [], "title": "\u6211\u60f3\u8981\u4eba\u75bc\u4eba\u5bf5"}, "threadStatus": 1, "regionId": 886, "barStatus": 0, "barId": 13, "postBy": {"utc": 1475567484000, "level": 2, "location": "\u6843\u5712\u5e02\u00b7\u53f0\u7063", "avatar": "http://filestoresg1.beetalkmobile.com:8081/file/6573555630099473590", "name": "\u9945\u9945"}, "id": 4620504}
