{"forum": {"content": "\u79cb\u666f", "images": ["http://filestoresg1.beetalkmobile.com:8081/file/2889488ff476f97898133339bf4328c6", "http://filestoresg1.beetalkmobile.com:8081/file/bad03fe97113d1fd09e67c45af80cbea", "http://filestoresg1.beetalkmobile.com:8081/file/def81be5b57df7198fe2591ff8ec0f12"], "urls": [], "title": "OSAKA"}, "threadStatus": 1, "regionId": 886, "barStatus": 0, "barId": 87, "postBy": {"utc": 1479303887000, "level": 9, "location": "", "avatar": "http://filestoresg1.beetalkmobile.com:8081/file/3672538163607274569", "name": "Sabadosedo"}, "id": 4875348}
