{"forum": {"content": "\u6258\u4ed6\u7684\u798f\uff0c\u8a8d\u8b58\u4e86\u9694\u58c1\u7403\u5834\u7684\u59b9\u5b50\ud83d\ude02", "images": ["http://filestoresg1.beetalkmobile.com:8081/file/96e31ed5ffd5ac61382361ed87692179"], "urls": [], "title": "\u8207\u67ef\u6279\u5408\u7167"}, "threadStatus": 0, "regionId": 886, "barStatus": 0, "barId": 33, "postBy": {"utc": 1477164511000, "level": 6, "location": "", "avatar": "http://filestoresg1.beetalkmobile.com:8081/file/8100695913488469505", "name": "j"}, "id": 4726423}
