{"forum": {"content": "\u8016~", "images": ["http://filestoresg1.beetalkmobile.com:8081/file/214839c5b90ad4faae50093f59660dad", "http://filestoresg1.beetalkmobile.com:8081/file/b49f41c2f71743d58396ad899a384cbe"], "urls": [], "title": "shit! I am single \u6211\u662f\u55ae\u8eab"}, "threadStatus": 1, "regionId": 886, "barStatus": 0, "barId": 205, "postBy": {"utc": 1472556482000, "level": 3, "location": "\u5f70\u5316\u7e23\u00b7\u53f0\u7063", "avatar": "http://filestoresg1.beetalkmobile.com:8081/file/6790511249606295808", "name": "Joker"}, "id": 4404496}
