{"forum": {"content": "\u6bcf\u6b21\u6ed1AZAR\u90fd\u6703\u6709\u4eba\u8aaa\u300c\u4f60\u662f\u6df7\u8840\u5152\u55ce\u300d ok \u8acb\u554f\u54ea\u500b\u9ede\u6df7\u4e86 \ud83d\ude02<br />\u597d\u83c8 \u6211\u5e03\u8fb2\u6df7\u5e03\u8fb2 \u5f88\u7d14 \ud83d\udc4d\ud83d\udc4d", "images": ["http://filestoresg1.beetalkmobile.com:8081/file/f4a09ec49c9a55e0d55796f128eaf628", "http://filestoresg1.beetalkmobile.com:8081/file/3c6c2b0c8e3a0a5eb3f6ea5a186023d3"], "urls": [], "title": "\u54ea\u4e00\u9ede\u6709\u6df7\u8840\u4e86"}, "threadStatus": 0, "regionId": 886, "barStatus": 0, "barId": 810, "postBy": {"utc": 1475519587000, "level": 3, "location": "\u53f0\u5317\u5e02\u00b7\u53f0\u7063", "avatar": "http://filestoresg1.beetalkmobile.com:8081/file/-1806160036150800894", "name": "Naaaaaaaaaa \ud83d\udc9c"}, "id": 4617893}
