{"forum": {"content": "\u6b61\u8fce\u5404\u4f4d\u4e00\u8d77\u8a0e\u8ad6\u5bf5\u7269XDDDD", "images": ["http://filestoresg1.beetalkmobile.com:8081/file/095390c5dab8ae348cabb0031467276e", "http://filestoresg1.beetalkmobile.com:8081/file/c0c4c70015aa8b3b48e8152e6cd7ae0e", "http://filestoresg1.beetalkmobile.com:8081/file/55a3842dcbedf8788ff37581a6e839ab", "http://filestoresg1.beetalkmobile.com:8081/file/e24b0e14d5ad42be5ccac2b4f8bbb4fa", "http://filestoresg1.beetalkmobile.com:8081/file/df6d462f3084ba2602b1c3d689332cb6", "http://filestoresg1.beetalkmobile.com:8081/file/7203c670fffc456123bada35a51d743a"], "urls": [], "title": "\u6211\u5bb6\u8c82\u5bf6\u5bf6"}, "threadStatus": 0, "regionId": 886, "barStatus": 0, "barId": 105, "postBy": {"utc": 1467659408000, "level": 3, "location": "\u6f8e\u6e56\u7e23\u00b7\u53f0\u7063", "avatar": "http://filestoresg1.beetalkmobile.com:8081/file/-8984028145068724389", "name": "ALEX"}, "id": 4048384}
