{"forum": {"content": "\u6709\u6c92\u6709\u5e25\u54e5\u53ef\u4ee5\u966a\u6211\u804a\u5929\u5440 \ud83d\ude02", "images": ["http://filestoresg1.beetalkmobile.com:8081/file/1571a5017ec977da5d5f32b8d251a0bf"], "urls": [], "title": "\u4f86\u804a\u5929\u554a\ud83d\ude0a"}, "threadStatus": 1, "regionId": 886, "barStatus": 0, "barId": 422, "postBy": {"utc": 1472520146000, "level": 7, "location": "\u96f2\u6797\u7e23\u00b7\u53f0\u7063", "avatar": "http://filestoresg1.beetalkmobile.com:8081/file/2676436707030092006", "name": "\uc5ec\uc790 \uce5c\uad6c"}, "id": 4401716}
