{"forum": {"content": "Keep\u4e0a\u7684\u6e1b\u80a5\u8ab2\u7a0b\u4e00\u5929\u96d6\u7136\u53ea\u670930\u5e7e\u5206\u9418\uff1b\u537b\u4e5f\u53ef\u4ee5\u6eff\u8eab\u5927\u6c57\u5440\u22ef\u22ef", "images": ["http://filestoresg1.beetalkmobile.com:8081/file/34606ac8373037690bcfa8a77447bf46", "http://filestoresg1.beetalkmobile.com:8081/file/203d57a84a5ef7c020ce49c605ef8708", "http://filestoresg1.beetalkmobile.com:8081/file/73bf2cd75b73ab861d6a7208d1cedb93"], "urls": [], "title": "Keep"}, "threadStatus": 0, "regionId": 886, "barStatus": 0, "barId": 66, "postBy": {"utc": 1477482423000, "level": 6, "location": "\u5357\u6295\u7e23\u00b7\u53f0\u7063", "avatar": "http://filestoresg1.beetalkmobile.com:8081/file/-3192638716403827451", "name": "Jeffer"}, "id": 4749039}
