{"forum": {"content": "\u8981\u600e\u9ebc\u4e00\u8d77\u4f54\u9818\u9053\u9928\u554a\uff1f<br />\u770b\u9053\u9928\u4e00\u6b21\u90fd\u6709\u597d\u5e7e\u96bb\u795e\u5947\u5bf6\u8c9d\u4f54\u9818", "images": ["http://filestoresg1.beetalkmobile.com:8081/file/91e57ee8849208f86b2a373956ace7e3"], "urls": [], "title": "\u95dc\u65bc\u9663\u71df\u548c\u4f54\u9818\u9053\u9928"}, "threadStatus": 0, "regionId": 886, "barStatus": 0, "barId": 820, "postBy": {"utc": 1470919456000, "level": 2, "location": "\u6843\u5712\u5e02\u00b7\u53f0\u7063", "avatar": "http://filestoresg1.beetalkmobile.com:8081/file/-8740654536782430818", "name": "\u5c0f\u8431"}, "id": 4283135}
