{"forum": {"content": "\u8a8d\u8b58\u65b0\u6367\u6cb9", "images": ["http://filestoresg1.beetalkmobile.com:8081/file/5e97ea54cbc60a88af681355e6c0f7d3"], "urls": [], "title": "UCH\u5927\u4e8c\u751f"}, "threadStatus": 0, "regionId": 886, "barStatus": 0, "barId": 757, "postBy": {"utc": 1473965156000, "level": 1, "location": "\u6843\u5712\u5e02\u00b7\u53f0\u7063", "avatar": "http://filestoresg1.beetalkmobile.com:8081/file/3067019516811464660", "name": "\u269c\ud83c\udfad\u6b63\u724c\u9673\u8001\u6fd5\ud83d\udcb1\u269c"}, "id": 4507749}
