{"forum": {"content": "\u4e0d\u597d\u610f\u601d\uff0c\u8acb\u554f\u8acb\u554f\u6709\u53f0\u4e2d\u5973\u5b69\u60f3\u5531\u6b4c\u55ce\uff1f<br />\u4e2d\u79cb\u6708\u5713\uff0c\u559d\u4e86\u9ede\u9152\uff0c\u597d\u60f3\u5531\u6b4c\u3002", "images": ["http://filestoresg1.beetalkmobile.com:8081/file/e5ad4dba73696257c40edd1e7d71e087"], "urls": [], "title": "\u8acb\u554f\u6709\u53f0\u4e2d\u5973\u5b69\u60f3\u5531\u6b4c\u55ce\uff1f\u6211\u597d\u60f3\u5531\u6b4c"}, "threadStatus": 1, "regionId": 886, "barStatus": 0, "barId": 205, "postBy": {"utc": 1473966700000, "level": 1, "location": "\u53f0\u4e2d\u5e02\u00b7\u53f0\u7063", "avatar": "http://filestoresg1.beetalkmobile.com:8081/file/-511103578299315533", "name": "\ud83c\uddefu s t i n \u5091 \u2705"}, "id": 4507829}
