{"forum": {"content": "\u62b1\u6b49\u50b7\u4f60\u5011\u773c\u775b\u4e86~\u54c8\u54c8<br />\u4f86\u804a\u5929\u8a8d\u8b58\u2606_\u2606\uff01\uff01", "images": ["http://filestoresg1.beetalkmobile.com:8081/file/13303436b3fa6b90454bc464ef36e2ad", "http://filestoresg1.beetalkmobile.com:8081/file/bf9d5f5f931653c6d01395a75d7bda70"], "urls": [], "title": "\u5982\u679c\u53ef\u4ee5\u8b93\u6211\u8a8d\u8b58\u59b3\u597d\u55ce\uff1f"}, "threadStatus": 1, "regionId": 886, "barStatus": 0, "barId": 383, "postBy": {"utc": 1471327913000, "level": 3, "location": "New Taipei City\u00b7Taiwan", "avatar": "http://filestoresg1.beetalkmobile.com:8081/file/805206453823674157", "name": "\u62b9\u8336\u63a7"}, "id": 4312784}
