{"forum": {"content": "\u670933\u6b72\u7684\u670b\u53cb\u9ebb \uff1f\uff1f\u51fa\u8072\u311b \u8a8d\u8b58\u4e00\u4e0b  \u54c8 \u5b9c\u862d\u6700\u597d\u311b \u54c8", "images": ["http://filestoresg1.beetalkmobile.com:8081/file/d4788f5e7fca2ee60ecb84aead90b83f", "http://filestoresg1.beetalkmobile.com:8081/file/e9fe5de114ac597049a3b62e2d7d94c6"], "urls": [], "title": "\u4ea4\u53cb \u55ae\u8eab \u8a8d\u8b58\u5504\uff1f\uff1f"}, "threadStatus": 0, "regionId": 886, "barStatus": 0, "barId": 205, "postBy": {"utc": 1478685565000, "level": 3, "location": "Yilan County\u00b7Taiwan", "avatar": "http://filestoresg1.beetalkmobile.com:8081/file/-8352732547630897028", "name": "\uc774\uacfc \u26bd"}, "id": 4832308}
