{"forum": {"content": "\u6211\u4e0d\u77e5\u9053\u9084\u6709\u9019\u7a2e\u53ef\u4ee5po\u6587\u7684\u529f\u80fd\uff5e", "images": ["http://filestoresg1.beetalkmobile.com:8081/file/dc902623c9e91d88b25e13bade5006cb"], "urls": [], "title": "\u6709\u6d3b\u4eba\u53ef\u4ee5\u804a\u7684\u55ce~"}, "threadStatus": 1, "regionId": 886, "barStatus": 0, "barId": 205, "postBy": {"utc": 1479220910000, "level": 2, "location": "Hsinchu City\u00b7Taiwan", "avatar": "http://filestoresg1.beetalkmobile.com:8081/file/-3786969813459698841", "name": "\u963f\u4fe1"}, "id": 4869751}
