{"forum": {"content": "\u9084\u662f\u5531\u5531\u6c92\u90a3\u9ebc\u5bb9\u6613\u5462<br />\u60b2\u50b7\u60c5\u6b4c\u7e3d\u662f\u90a3\u9ebc\u591a<br />\u4f55\u6642\u5531\u7684\u624d\u80fd\u8b8a\u7537\u5973\u5c0d\u5531\u60c5\u6b4c\u5462", "images": ["http://filestoresg1.beetalkmobile.com:8081/file/9bd5c213d29865248f7f2fed6a5be463"], "urls": [], "title": "\u60c5\u4eba\u7bc0\u2026\u2026\u770b\u4f86\u9084\u662f\u7e7c\u7e8c\u5531\u8457\u55ae\u8eab\u60c5\u6b4c\u597d\u4e86"}, "threadStatus": 0, "regionId": 886, "barStatus": 0, "barId": 537, "postBy": {"utc": 1470662239000, "level": 1, "location": "Tainan City\u00b7Taiwan", "avatar": "http://filestoresg1.beetalkmobile.com:8081/file/5950266664708670722", "name": "Star"}, "id": 4264276}
