{"forum": {"content": "\u9019\u88e1\u771f\u7684\u4ea4\u5f97\u5230\u670b\u53cb\u55ce\ud83e\udd14", "images": ["http://filestoresg1.beetalkmobile.com:8081/file/ae8f62a586863cc65b18b58467a62411"], "urls": [], "title": "\u55e8 \u4e0d\u5acc\u68c4\u7684\u8a71\u4f86\u804a\u5929\u8a8d\u8b58\u4e00\u4e0b"}, "threadStatus": 0, "regionId": 886, "barStatus": 0, "barId": 205, "postBy": {"utc": 1480927265000, "level": 2, "location": "\u53f0\u4e2d\u5e02\u00b7\u53f0\u7063", "avatar": "http://filestoresg1.beetalkmobile.com:8081/file/6766696932841707266", "name": "\u262e\ufe0fMuska\u269b\ufe0f"}, "id": 4983715}
