{"forum": {"content": "\u6211\u53ea\u662f\u83dc\u9ce5\u73a9\u5bb6 \uff01", "images": ["http://filestoresg1.beetalkmobile.com:8081/file/bfdfa06b8122771b77d14aeae36d9a57", "http://filestoresg1.beetalkmobile.com:8081/file/0552f257a1b71ff579a8733eb2c2bac3", "http://filestoresg1.beetalkmobile.com:8081/file/49c71a16c9d416abdf7ab4bbda14893e", "http://filestoresg1.beetalkmobile.com:8081/file/d20bef11b06db8a6fdb6f4bc00d1e672", "http://filestoresg1.beetalkmobile.com:8081/file/4c2266524ccf502f69e2c02e991baee5"], "urls": [], "title": "\u4eba\u751f\u7b2c\u4e00\u500bRG \uff0c\u4e00\u500b\u56de\u61b6\u7684\u6a5f\u9ad4"}, "threadStatus": 0, "regionId": 886, "barStatus": 0, "barId": 207, "postBy": {"utc": 1467119425000, "level": 3, "location": "\u65b0\u5317\u5e02\u00b7\u53f0\u7063", "avatar": "http://filestoresg1.beetalkmobile.com:8081/file/-1447058454153395910", "name": "20dollars"}, "id": 4010340}
