{"forum": {"content": "\u5c0f\u59b9\u6211\u76ee\u524d\u92803<br />\u6709\u54ea\u5473\u5927\u54e5\u5927\u59d0 \u80fd\u966a\u6253\u722c\u4e0a\u91d1\u724c<br />\u4e0b\u9762\u7559\u8a00\ud83d\udc93\ud83d\udc93", "images": ["http://filestoresg1.beetalkmobile.com:8081/file/4d64fe831e74581d069aef935eb97d7e"], "urls": [], "title": "\u6c42\u5e36\u6211\u722c\u5206 \u597d\u54aa\ud83d\udc93\ud83d\udc93"}, "threadStatus": 0, "regionId": 886, "barStatus": 0, "barId": 60, "postBy": {"utc": 1476630969000, "level": 2, "location": "Nantou County\u00b7Taiwan", "avatar": "http://filestoresg1.beetalkmobile.com:8081/file/-2253522734338086640", "name": "\ud83c\ude32"}, "id": 4687432}
