{"forum": {"content": "\u770b\u5230\u4ed6\u5728\u6293\u6c99\u767c\u53ea\u597d\u4e00\u8d77\u6293\u4e86\ud83d\ude02\ud83d\ude02\ud83d\ude02", "images": ["http://filestoresg1.beetalkmobile.com:8081/file/531e9e397453b23296e5163c76ec7e94", "http://filestoresg1.beetalkmobile.com:8081/file/4bca8c39f63bf551c2d98bbbf96f6aa2"], "urls": [], "title": "\u8c93\u722a\u6293\u4e00\u8d77\u6293\ud83d\ude02\ud83d\ude02\ud83d\ude02"}, "threadStatus": 1, "regionId": 886, "barStatus": 0, "barId": 751, "postBy": {"utc": 1480746207000, "level": 2, "location": "\u53f0\u4e2d\u5e02\u00b7\u53f0\u7063", "avatar": "http://filestoresg1.beetalkmobile.com:8081/file/8052165673896824066", "name": "\u6211\u6709\u4e00\u96bb\u5c0f\u6bdb\u718a"}, "id": 4971243}
