{"forum": {"content": "\u55e8\u55e8\u55e8 \u6211\u662f\u5c4f\u6771\u4eba<br />\u6148\u60e0\u91ab\u5c08\u7269\u7406\u6cbb\u7642\u79d1\u65b0\u751f\ud83d\ude4b<br />\u60f3\u804a\u5929\u7684\u8a71\u53ef\u4ee5\u52a0\u6211FB\ud83d\ude0a\ud83d\ude0a", "images": ["http://filestoresg1.beetalkmobile.com:8081/file/30db5c3da542e3d4aec265933a113e32", "http://filestoresg1.beetalkmobile.com:8081/file/27e277091c58ac740d7c21dc31524525", "http://filestoresg1.beetalkmobile.com:8081/file/c647834a99da8bf9b3263e08097b0e14", "http://filestoresg1.beetalkmobile.com:8081/file/8c1d70dd8d64574ebf778963c7b7718c", "http://filestoresg1.beetalkmobile.com:8081/file/08f63993db7af1598209baa45cf04bd2", "http://filestoresg1.beetalkmobile.com:8081/file/c67d2dbc021481ba34ec71183be79dd4"], "urls": [], "title": "\u5feb\u9032\u4f86\u554a\ud83d\ude4c"}, "threadStatus": 1, "regionId": 886, "barStatus": 0, "barId": 676, "postBy": {"utc": 1470478865000, "level": 2, "location": "\u5c4f\u6771\u7e23\u00b7\u53f0\u7063", "avatar": "http://filestoresg1.beetalkmobile.com:8081/file/-6229739420036290302", "name": "\u8431\u2764"}, "id": 4250330}
