{"forum": {"content": "\u5c0f\u5f1f\u677f\u6a4b\u4eba178/64\uff0c\u4e0d\u83f8\u4e0d\u9152\uff0c\u8208\u8da3\u662f\u904b\u52d5\u8ddf\u770b\u96fb\u5f71\uff0c\u96d6\u7136\u5e73\u5e38\u5f88\u5fd9\uff0c\u4f46\u5230\u5047\u65e5\u5c31\u9592\u5230\u767c\u8352\uff0c\u8aa0\u5fb5\u4e00\u4f4d\u80fd\u5920\u966a\u6211\u5ea6\u904e\u7121\u804a\u7684\u5047\u65e5\u7684\u5973\u5b69\uff0c\u5403\u98ef\u901b\u8857\u90fdok\uff0c\u8aa0\u8005\u79c1\u5bc6\u3002", "images": ["http://filestoresg1.beetalkmobile.com:8081/file/a320a754044f04b94c69fa1ed1069d1d", "http://filestoresg1.beetalkmobile.com:8081/file/0070c295169514d9f83eaaf61c13953a", "http://filestoresg1.beetalkmobile.com:8081/file/542b98e25a61cc570d8e94c0a2184c2d", "http://filestoresg1.beetalkmobile.com:8081/file/24aa8c17dea8850afa499945a883d88d"], "urls": [], "title": "\u4e0d\u60f3\u5728\u9b6f\u4e86 \u8aa0\u5fb5\u5973\u53cb"}, "threadStatus": 0, "regionId": 886, "barStatus": 0, "barId": 205, "postBy": {"utc": 1474711032000, "level": 3, "location": "\u65b0\u5317\u5e02\u00b7\u53f0\u7063", "avatar": "http://filestoresg1.beetalkmobile.com:8081/file/-9112766660835555309", "name": "Alan"}, "id": 4560936}
