{"forum": {"content": "\u4e0a\u8272\u524d\u5f8c", "images": ["http://filestoresg1.beetalkmobile.com:8081/file/f3e762d70d06d56d354515d2f21ce11e", "http://filestoresg1.beetalkmobile.com:8081/file/d8ff8af3f3c434179b10934ad2c7c789"], "urls": [], "title": "\u5c0f\u6b4c\u624b\ud83d\ude09"}, "threadStatus": 0, "regionId": 886, "barStatus": 0, "barId": 605, "postBy": {"utc": 1474940827000, "level": 2, "location": "\u65b0\u7af9\u7e23\u00b7\u53f0\u7063", "avatar": "http://filestoresg1.beetalkmobile.com:8081/file/-6301937743803359336", "name": "\u2022\u20ac\u963f\u561f\u6bdb"}, "id": 4577295}
