{"forum": {"content": "\u5404\u4f4d\u639b\u6b65\u69cd\u5175\u7684\u5144\u5f1f\u59d0\u59b9\u5011<br />\u5982\u679c\u4f60\u5011\u6c92\u7e8c\u7c3d    \u6216\u662f\u5347\u58eb\u5b98\u7684<br />\u73fe\u5728  \u5c31\u662f\u5c6c\u65bc\u767e\u59d3\u4e86<br /><br />\u5c0f\u5f1f\u4e0d\u624d  \u7e8c\u7c3d1\u5e74  \u5f9e\u73fe\u5728\u958b\u59cb  \u53c8\u91cd\u7b97365\u4e86<br />\u8a31\u591a\u5347\u7684\u5feb\u7684  \u61c9\u8a72\u90fd\u4e2d\u58eb\u4e86\u5427   \u52a0\u6cb9\u54e6<br /><br /><br />@@\u7a81\u7136\u795e\u7d93\u63a5\u932f  \u60f3po\u9019\u500b\ud83d\ude02\ud83d\ude02\ud83d\ude02", "images": ["http://filestoresg1.beetalkmobile.com:8081/file/9437701e1a60188ae4f694cca3f58f8f"], "urls": [], "title": "\u7d66101-2"}, "threadStatus": 0, "regionId": 886, "barStatus": 0, "barId": 704, "postBy": {"utc": 1473615808000, "level": 3, "location": "\u82d7\u6817\u7e23\u00b7\u53f0\u7063", "avatar": "http://filestoresg1.beetalkmobile.com:8081/file/-3102824010995230899", "name": "Way"}, "id": 4483421}
