{"forum": {"content": "\u516b\u5e74\u7d1a\u751f\uff01\u958b\u59cb\u8a8d\u8b58\u56c9\uff01", "images": ["http://filestoresg1.beetalkmobile.com:8081/file/e2878b30be2d40f4f29030b59ef7ceae", "http://filestoresg1.beetalkmobile.com:8081/file/e67de6328a76c4fbc2b0ef7ca5ba525a", "http://filestoresg1.beetalkmobile.com:8081/file/93901fe34fad6e5be46bde51c65cbfb8", "http://filestoresg1.beetalkmobile.com:8081/file/d0290df9ad235f0906256ed2e9ad6f0a"], "urls": [], "title": "1992 \u5c04\u624b \u9ad8\u96c4\u4eba\uff01 \u55e8\u56c9"}, "threadStatus": 0, "regionId": 886, "barStatus": 0, "barId": 748, "postBy": {"utc": 1467456214000, "level": 1, "location": "\u9ad8\u96c4\u5e02\u00b7\u53f0\u7063", "avatar": "http://filestoresg1.beetalkmobile.com:8081/file/-2818491401825183821", "name": "\u97d3\u5347"}, "id": 4033538}
