{"forum": {"content": "\u820c\u982d\u9732\u4e00\u7247\uff0c\u65e5\u5f8c\u597d\u76f8\u898b\u3002", "images": ["http://filestoresg1.beetalkmobile.com:8081/file/d2ca2e59cd189df8c17bfb103ed16e8d", "http://filestoresg1.beetalkmobile.com:8081/file/c8ba4d01cddde4991840d3b96286261c"], "urls": [], "title": "\u59d0\u5074\u81e5\u6c92\u4e8b\uff0c\u6c92\u4e8b\u90fd\u5074\u81e5"}, "threadStatus": 0, "regionId": 886, "barStatus": 0, "barId": 105, "postBy": {"utc": 1473352545000, "level": 2, "location": "\u65b0\u5317\u5e02\u00b7\u53f0\u7063", "avatar": "http://filestoresg1.beetalkmobile.com:8081/file/9001359765915286785", "name": "\uff2d\uff21\u00ae\ufe0f\uff34\uff29\uff2e"}, "id": 4463939}
