{"forum": {"content": "\u8acb\u6b63\u4eba\u541b\u5b50\u4f86\u52a0\u9019\u5718\u3002\u3002\u963f\u54f2\u3002\u8ca0\u5718\u4e3b\u3002\u4e0d\u804a\u8272\u60c5\u3002\u53ea\u559d\u9152\u3002\u5531\u6b4c\u3002\u71d2\u70e4\u5e97\u3002\u3002", "images": ["http://filestoresg1.beetalkmobile.com:8081/file/8615d02dc27c2db3a88a3015164e61ae"], "urls": [], "title": "\u6b61\u6b61\u516c\u4e3b"}, "threadStatus": 1, "regionId": 886, "barStatus": 0, "barId": 687, "postBy": {"utc": 1472847955000, "level": 2, "location": "\u53f0\u4e2d\u5e02\u00b7\u53f0\u7063", "avatar": "http://filestoresg1.beetalkmobile.com:8081/file/-460319322421103360", "name": "\u9673"}, "id": 4426391}
