{"forum": {"content": "\u7d42\u65bc15\u5929\u4e86<br />\u5c0f\u5bf6\u8c9d\u5feb\u9577\u5927\u554a<br />\ud83d\ude0d\ud83d\ude0d\ud83d\ude0d\ud83d\ude0d\ud83d\ude0d\ud83d\ude0d\ud83d\ude0d<br />\u671f\u5f85\u5929\u5929\u5e36\u8457\u4f60\u5011\u5230\u8655\u8dd1", "images": ["http://filestoresg1.beetalkmobile.com:8081/file/2f8b621dd565c47506b6f49ee476fc20", "http://filestoresg1.beetalkmobile.com:8081/file/11ce349b45e332594def196a6e573cc9", "http://filestoresg1.beetalkmobile.com:8081/file/dee8e2e2080128352405390adc7d450c", "http://filestoresg1.beetalkmobile.com:8081/file/f8d901d9d8eaae939e03053141d7515b"], "urls": [], "title": "\u963f\u62c9\u65af\u52a0\u96ea\u6a47\u72ac"}, "threadStatus": 1, "regionId": 886, "barStatus": 0, "barId": 105, "postBy": {"utc": 1470129491000, "level": 3, "location": "\u65b0\u5317\u5e02\u00b7\u53f0\u7063", "avatar": "http://filestoresg1.beetalkmobile.com:8081/file/5341407707838270730", "name": "ANNA\u2708\ufe0f"}, "id": 4225226}
