{"forum": {"content": "\u5230\u73fe\u5728\u9084\u662f\u55ae\u8eab\uff0c\u55ae\u8eab17\u5e74\uff0c\u8ab0\u8981\u8a8d\u8b58\u4ffa\uff1f", "images": ["http://filestoresg1.beetalkmobile.com:8081/file/fcc68f7079cc6959eb1fa45c4df87286"], "urls": [], "title": "\u55ae\u8eab\u7684\u65e5\u5b50\uff0c\u7e3d\u662f\u7121\u8da3"}, "threadStatus": 0, "regionId": 886, "barStatus": 0, "barId": 205, "postBy": {"utc": 1470669294000, "level": 1, "location": "\u6843\u5712\u5e02\u00b7\u53f0\u7063", "avatar": "http://filestoresg1.beetalkmobile.com:8081/file/-7190334353618141291", "name": "\u8aa0\u5be6\u7684\u679c\u5be6"}, "id": 4265171}
