{"forum": {"content": "\u65e9\u5b89\uff0c<br />I want my kisses back from you<br />,\u6211\u8981\u6211\u7684\u543b\u5f97\u5230\u4f60\u7684\u56de\u61c9\uff01<br />\u9019\u9996\u6b4c\u6709\u4e00\u7a2e\u7279\u5225\u7684\u9b54\u529b\u5438\u5f15\u8457\u4eba\u60f3\u7e7c\u7e8c\u807d\u3002", "images": [], "urls": [{"url": "https://youtu.be/aydKPFaf4oY", "thumbUrl": "https://i.ytimg.com/vi/aydKPFaf4oY/maxresdefault.jpg", "description": "\u266b Stream it on Spotify: https://open.spotify.com/track/2vu1gO7FXJ35Vz71Ra4hnz \u266b Get it on iTunes: ht", "title": "Matthew Koma - Kisses Back"}], "title": "from you!"}, "threadStatus": 0, "regionId": 886, "barStatus": 0, "barId": 54, "postBy": {"utc": 1480553533000, "level": 9, "location": "\u57fa\u9686\u5e02\u00b7\u53f0\u7063", "avatar": "http://filestoresg1.beetalkmobile.com:8081/file/730549627352538369", "name": "\u7da0\u8c46"}, "id": 4959083}
