{"forum": {"content": "<br /> \u55e8\uff5e\u4f60\u9084\u4e0d\u4f86\u8a8d\u8b58\u6211\u55ce\uff1f", "images": ["http://filestoresg1.beetalkmobile.com:8081/file/47c09c1bcd32e3835487865a4e5819a9"], "urls": [], "title": "\u4f86\u8a8d\u8b58\u6211\u5427\uff5e"}, "threadStatus": 1, "regionId": 886, "barStatus": 0, "barId": 383, "postBy": {"utc": 1467514383000, "level": 21, "location": "\u65b0\u5317\u5e02\u00b7\u53f0\u7063", "avatar": "http://filestoresg1.beetalkmobile.com:8081/file/-7403453785409893192", "name": " \u59cd \u59cd\ud83c\udf38"}, "id": 4037417}
