{"forum": {"content": "\u842c\u8056\u7bc0\u599d\ud83d\ude04\ud83d\ude04\ud83d\ude04", "images": ["http://filestoresg1.beetalkmobile.com:8081/file/5ffa8f07dc610e0df04a1240f564fce3", "http://filestoresg1.beetalkmobile.com:8081/file/3dbb2b241bf5811a8a2ee10c2425d50d", "http://filestoresg1.beetalkmobile.com:8081/file/bcf8dc4630814040b2ae7383d6c7a530"], "urls": [], "title": "\u4e0d\u7d66\u7cd6\u5c31\u6417\u86cb"}, "threadStatus": 0, "regionId": 886, "barStatus": 0, "barId": 706, "postBy": {"utc": 1477839122000, "level": 7, "location": "\u53f0\u4e2d\u5e02\u00b7\u53f0\u7063", "avatar": "http://filestoresg1.beetalkmobile.com:8081/file/-5326304786385449472", "name": "\u5c0f\u9f8d"}, "id": 4774406}
