{"forum": {"content": "\u59d0\u59b9\u5011\u5927\u5b78\u5f8c\u597d\u591a\u90fd\u5230\u5916\u7e23\u5e02\u5b9a\u5c45\u4e86<br />\u7537\u670b\u53cb\u5e0c\u671b\u6211\u80fd\u518d\u6709\u81ea\u5df1\u7684\u59d0\u59b9\u7fa4\u624d\u4e0d\u6703\u7121\u804a<br /><br />\u6709\u6c92\u6709\u4eba\u8ddf\u6211\u4e00\u6a23\u56f0\u64fe\ud83d\ude02\ud83d\ude02\ud83d\ude02<br />\u5076\u723e\u53ef\u4ee5\u8ddf\u6211\u901b\u8857\u5403\u9ede\u5fc3\u7684\ud83d\ude1a", "images": ["http://filestoresg1.beetalkmobile.com:8081/file/ea656b9d1979d2a210f6d16e10858332"], "urls": [], "title": "\u5fb5\u6c42\u53f0\u4e2d\u95a8\u871c~~~\ud83d\ude02"}, "threadStatus": 1, "regionId": 886, "barStatus": 0, "barId": 208, "postBy": {"utc": 1470219800000, "level": 1, "location": "\u53f0\u4e2d\u5e02\u00b7\u53f0\u7063", "avatar": "http://filestoresg1.beetalkmobile.com:8081/file/-1126455141697497804", "name": "\u81fb\u81fb\ud83e\udd13"}, "id": 4231821}
