{"forum": {"content": "\u53f0\u4e2d\ud83d\udccd", "images": ["http://filestoresg1.beetalkmobile.com:8081/file/764b215ca94d337e4b67ee9e02686439", "http://filestoresg1.beetalkmobile.com:8081/file/e4867cd7d4965060db0525e8868630c5"], "urls": [], "title": "\u51b0\u6dc7\u6dcb"}, "threadStatus": 0, "regionId": 886, "barStatus": 0, "barId": 208, "postBy": {"utc": 1470749937000, "level": 2, "location": "", "avatar": "http://filestoresg1.beetalkmobile.com:8081/file/248594083408397569", "name": "\u5982\u59b9"}, "id": 4271032}
