{"forum": {"content": "\u6416\u982d\u5606\u606f((((((((((\u5509", "images": ["http://filestoresg1.beetalkmobile.com:8081/file/61f89e87d5e63d8fface6153ff8b966c"], "urls": [], "title": "\u5c0f\u670b\u53cb\u554a\uff0c\u4f60\u8981\u4f5c\u5f0a\u4e5f\u627e\u500b\u53b2\u5bb3\u7684~"}, "threadStatus": 0, "regionId": 886, "barStatus": 0, "barId": 10, "postBy": {"utc": 1467212614000, "level": 22, "location": "\u5b9c\u862d\u7e23\u00b7\u53f0\u7063", "avatar": "http://filestoresg1.beetalkmobile.com:8081/file/3223834066961541322", "name": "\u51cc\u73b2"}, "id": 4017409}
