{"forum": {"content": "\u662f\u55ae\u8eab\u5c31\u505a\u670b\u53cb\u5427\uff01<br />\u6211\u662f\u9713\u5b50<br />\u73fe\u8b80\u9ad8\u96c4\u61c9\u7528\u79d1\u6280\u5927\u5b78<br />\u8b80\u5c08\u696d\u82f1\u6587\u8207\u6559\u5b78\u79d1\u6280\u7cfb<br />\u78a9\u58eb\u4e00\u5e74\u7d1a<br />\u9084\u662f\u5b78\u751f\u54e6\uff01", "images": ["http://filestoresg1.beetalkmobile.com:8081/file/839520fd336224d7b7c21aed8ee359b6", "http://filestoresg1.beetalkmobile.com:8081/file/031435109b8a18a3c73169e98a330ff8", "http://filestoresg1.beetalkmobile.com:8081/file/295b56e95994e03742841d546d4cef3b", "http://filestoresg1.beetalkmobile.com:8081/file/aa8fa480e6528f2a9e2d7d17862adbb8", "http://filestoresg1.beetalkmobile.com:8081/file/3b0e502620cd4b66db33545a6302e40a", "http://filestoresg1.beetalkmobile.com:8081/file/d2771bfa675c3b4c42eb2830d6b09fb3"], "urls": [], "title": "\u505a\u670b\u53cb\u5427"}, "threadStatus": 0, "regionId": 886, "barStatus": 0, "barId": 205, "postBy": {"utc": 1473521100000, "level": 0, "location": "\u9ad8\u96c4\u5e02\u00b7\u53f0\u7063", "avatar": "http://filestoresg1.beetalkmobile.com:8081/file/-6704594303183221350", "name": "\u5922\u8431"}, "id": 4476120}
