{"forum": {"content": "\u59b9\u5b50\u6211\u5f9e\u4e8b\u4e862\u5e74\u7f8e\u9aee\u52a9\u7406<br />\u6700\u8fd1\u60f3\u5f80\u65b0\u5a18\u79d8\u66f8\u90a3\u88e1\u767c\u5c55<br />\u59b9\u5b50\u60f3\u5b78\u7fd2\u7f8e\u5bb9\u5f69\u599d\u985e\u7684<br />\u6843\u5712\u5340\u6709\u54ea\u500b\u5e97\u5bb6\u7f3a\u7f8e\u5bb9\u5f69\u599d\u52a9\u7406\u55ce\uff1f", "images": ["http://filestoresg1.beetalkmobile.com:8081/file/0d961644de7ee5f9940dbcda2470b6c6"], "urls": [], "title": "\u60f3\u554f\u554f"}, "threadStatus": 0, "regionId": 886, "barStatus": 0, "barId": 706, "postBy": {"utc": 1471246808000, "level": 1, "location": "\u6843\u5712\u5e02\u00b7\u53f0\u7063", "avatar": "http://filestoresg1.beetalkmobile.com:8081/file/-4694999298990629836", "name": "\u6b64\u7528\u6236\u5df2\u6d88\u5931"}, "id": 4307060}
