{"forum": {"content": "\u87fe\u870d\u5c71\u6e56", "images": ["http://filestoresg1.beetalkmobile.com:8081/file/a3269c91aed6b1b3db6105b1074db19f", "http://filestoresg1.beetalkmobile.com:8081/file/72c9745bb94ba06a154e0373c0a4870d", "http://filestoresg1.beetalkmobile.com:8081/file/25e1c34c819db1b95aff724669170d35", "http://filestoresg1.beetalkmobile.com:8081/file/d9865ffec4b94e4382b26a63ac631ea5", "http://filestoresg1.beetalkmobile.com:8081/file/376a5f6f7cf8ae541c1cc68fb641b9e6", "http://filestoresg1.beetalkmobile.com:8081/file/0659eee0df4fd72383ae358634da5776"], "urls": [], "title": "\u4e09\u5cfd\u87fe\u870d\u5c71\u8c37"}, "threadStatus": 0, "regionId": 886, "barStatus": 0, "barId": 85, "postBy": {"utc": 1473940869000, "level": 27, "location": "\u65b0\u5317\u5e02\u00b7\u53f0\u7063", "avatar": "http://filestoresg1.beetalkmobile.com:8081/file/-8785875248541826410", "name": "\ud83d\udc95\u5ed6\u54e1\u5916\ud83d\udcf7"}, "id": 4505356}
