{"forum": {"content": "<br /><br />\u771f\u60f3\u8981\u591c\u751f\u6d3b\u5594", "images": ["http://filestoresg1.beetalkmobile.com:8081/file/dff774e4a187379814b15754a165f21a", "http://filestoresg1.beetalkmobile.com:8081/file/a161bbf07d01e5572a801547ac01f31a"], "urls": [], "title": "\u597d\u591a\u4eba\u6b50"}, "threadStatus": 0, "regionId": 886, "barStatus": 0, "barId": 676, "postBy": {"utc": 1472909953000, "level": 8, "location": "\u5c4f\u6771\u7e23\u00b7\u53f0\u7063", "avatar": "http://filestoresg1.beetalkmobile.com:8081/file/-3916750683059952125", "name": "\u5509\uff01\u7d55\u671b\u7684\u4e16\u754c\u3002"}, "id": 4430743}
