{"forum": {"content": "\u53f0\u4e2d\u570b\u7acb\u7f8e\u8853\u9928\u767e\u5206\u4e4b\u767e\u662f\u626d\u86cb\u602a\u5de2\u7a74\u5427\uff01", "images": ["http://filestoresg1.beetalkmobile.com:8081/file/544ead95d478ac7073166d6c616efb09"], "urls": [], "title": "\u53f0\u4e2d\u570b\u7acb\u7f8e\u8853\u9928\u5468\u570d\u597d\u591a\u626d\u86cb\u602a"}, "threadStatus": 1, "regionId": 886, "barStatus": 0, "barId": 820, "postBy": {"utc": 1478258134000, "level": 2, "location": "\u53f0\u4e2d\u5e02\u00b7\u53f0\u7063", "avatar": "http://filestoresg1.beetalkmobile.com:8081/file/1", "name": "\u3000"}, "id": 4802623}
