{"forum": {"content": "\u5149\u660e\u570b\u4e2d<br />14\u6b72<br />\u6c34\u74f6\u5ea7", "images": ["http://filestoresg1.beetalkmobile.com:8081/file/b5dbeb345e34164b28745a9765de53da"], "urls": [], "title": "\u570b\u4e09\u751f"}, "threadStatus": 1, "regionId": 886, "barStatus": 0, "barId": 512, "postBy": {"utc": 1473173722000, "level": 4, "location": "\u6843\u5712\u5e02\u00b7\u53f0\u7063", "avatar": "http://filestoresg1.beetalkmobile.com:8081/file/1668636456548963584", "name": "\u5446\u5446"}, "id": 4450777}
