{"forum": {"content": "angelic voice \u2026", "images": [], "urls": [{"url": "https://m.youtube.com/watch?v=QS_IZavGaKo", "thumbUrl": "https://i.ytimg.com/vi/QS_IZavGaKo/default.jpg", "description": "Lyrics:\r\nRealising a form out of stone,\r\nSet hands moving.\r\nRoan shaped his heart,\r\nThrough his work", "title": "Turn of the Century by Yes"}], "title": "turn of the century by yes "}, "threadStatus": 0, "regionId": 886, "barStatus": 0, "barId": 54, "postBy": {"utc": 1475538219000, "level": 12, "location": "\u5b9c\u862d\u7e23\u00b7\u53f0\u7063", "avatar": "http://filestoresg1.beetalkmobile.com:8081/file/5954747174160257302", "name": "nektartab"}, "id": 4618496}
