{"forum": {"content": "\u5411\u4e0a\u770b20\u5e74\u524d\u7684\u5927\u54e5\u5df2\u670960\uff0c\u5411\u4e0b\u770b\u66fe\u62b1\u5728\u624b\u4e0a\u7684\u5c0f\u5a03\u90fd\u9577\u7684\u6bd4\u6211\u9ad8\u4e86\uff0c\u800c\u8aaa\u8001\u6c92\u5e7e\u6839\u767d\u9aee\uff0c\u8b1b\u5e74\u8f15\u4e5f\u6bd4\u6c92\u9bae\u8089\u5e02\u5834\u5438\u5f15\u4eba\uff0c\u4e2d\u9593\u4efd\u5b50\uff0c\u4e0d\u4e0a\u4e0d\u4e0b", "images": ["http://filestoresg1.beetalkmobile.com:8081/file/f3caf93f9e0d47b53340ffd0a2c7e302", "http://filestoresg1.beetalkmobile.com:8081/file/81114b056d9d6043d2a78a7ec4a4edac", "http://filestoresg1.beetalkmobile.com:8081/file/d1c1151e79b0086397e53531b09cbf9a"], "urls": [], "title": "\u4e2d\u6bb5\u73ed\u5230\uff085\u73ed\uff09"}, "threadStatus": 1, "regionId": 886, "barStatus": 0, "barId": 746, "postBy": {"utc": 1476711602000, "level": 1, "location": "\u65b0\u5317\u5e02\u00b7\u53f0\u7063", "avatar": "http://filestoresg1.beetalkmobile.com:8081/file/2193027620755517954", "name": "\u7279\u816b\u90e8\u968aAaron\u7d0b\u89aa\u7d44"}, "id": 4692018}
